mqtt_randompub/__init__.py
mqtt_randompub/mqtt_randompub.py
mqtt_randompub/opthandling.py
mqtt_randompub-0.2.2.dist-info/AUTHORS
mqtt_randompub-0.2.2.dist-info/LICENSE
mqtt_randompub-0.2.2.dist-info/METADATA
mqtt_randompub-0.2.2.dist-info/WHEEL
mqtt_randompub-0.2.2.dist-info/entry_points.txt
mqtt_randompub-0.2.2.dist-info/top_level.txt
mqtt_randompub-0.2.2.dist-info/RECORD
