Metadata-Version: 2.1
Name: mqtt-randompub
Version: 0.2.2
Summary: Tool for generating MQTT messages on various topics
Home-page: https://github.com/fabaff/mqtt-randompub/
Author: Fabian Affolter
Author-email: fabian@affolter-engineering.ch
Maintainer: Fabian Affolter
Maintainer-email: fabian@affolter-engineering.ch
License: MIT
Keywords: MQTT,System,Messages
Platform: Linux
Classifier: Development Status :: 4 - Beta
Classifier: Environment :: Console
Classifier: Intended Audience :: System Administrators
Classifier: Intended Audience :: Developers
Classifier: License :: OSI Approved :: MIT License
Classifier: Operating System :: POSIX
Classifier: Programming Language :: Python
Classifier: Programming Language :: Python :: 3.8
Classifier: Programming Language :: Python :: 3.9
Classifier: Programming Language :: Python :: 3.10
Classifier: Topic :: Communications
Classifier: Topic :: Internet
Classifier: Topic :: System
Classifier: Topic :: System :: Networking
Requires-Dist: paho-mqtt
